[{"timestamp": "20:42:49 08-02-2024", "mexc": "https://futures.mexc.com/exchange/CTSI_USDT?type=linear_swap", "symbol": "CTSIUSDT", "price": " 1.285 ", "price24": "3.676", "vol": "0.088 ", "vol24": "89,125,397.128"}, {"timestamp": "20:42:49 08-02-2024", "mexc": "https://futures.mexc.com/exchange/SUI_USDT?type=linear_swap", "symbol": "SUIUSDC", "price": " 1.091 ", "price24": "2.097", "vol": "8.597 ", "vol24": "1,397,302.573"}, {"timestamp": "20:42:49 08-02-2024", "mexc": "https://futures.mexc.com/exchange/SUI_USDT?type=linear_swap", "symbol": "SUIUSDT", "price": " 0.992 ", "price24": "-0.476", "vol": "0.61 ", "vol24": "354,916,685.757"}, {"timestamp": "20:42:49 08-02-2024", "mexc": "https://futures.mexc.com/exchange/FLOW_USDT?type=linear_swap", "symbol": "FLOWUSDT", "price": " 0.753 ", "price24": "8.221", "vol": "1.276 ", "vol24": "25,423,845.268"}, {"timestamp": "20:42:49 08-02-2024", "mexc": "https://futures.mexc.com/exchange/INJ_USDT?type=linear_swap", "symbol": "INJUSDT", "price": " 0.63 ", "price24": "0.317", "vol": "-1.056 ", "vol24": "173,098,603.254"}, {"timestamp": "20:42:49 08-02-2024", "mexc": "https://futures.mexc.com/exchange/NMR_USDT?type=linear_swap", "symbol": "NMRUSDT", "price": " 0.587 ", "price24": "-2.12", "vol": "-0.117 ", "vol24": "57,628,810.56"}, {"timestamp": "20:42:49 08-02-2024", "mexc": "https://futures.mexc.com/exchange/OMG_USDT?type=linear_swap", "symbol": "OMGUSDT", "price": " 0.555 ", "price24": "1.946", "vol": "0.632 ", "vol24": "6,763,657.746"}, {"timestamp": "20:42:49 08-02-2024", "mexc": "https://futures.mexc.com/exchange/OP_USDT?type=linear_swap", "symbol": "OPUSDT", "price": " 0.511 ", "price24": "-3.105", "vol": "-0.205 ", "vol24": "272,420,988.654"}, {"timestamp": "20:42:49 08-02-2024", "mexc": "https://futures.mexc.com/exchange/HOOK_USDT?type=linear_swap", "symbol": "HOOKUSDT", "price": " 0.477 ", "price24": "1.811", "vol": "0.222 ", "vol24": "15,165,365.774"}, {"timestamp": "20:42:49 08-02-2024", "mexc": "https://futures.mexc.com/exchange/AMB_USDT?type=linear_swap", "symbol": "AMBUSDT", "price": " 0.417 ", "price24": "-0.341", "vol": "-0.82 ", "vol24": "32,957,040.907"}]